chips/__init__.py
chips/_version.py
chips/banks/__init__.py
chips/banks/fingerprint.py
chips/banks/serial.py
chips/bin/__init__.py
chips/bin/bank_search.py
chips/data/README.md
chips/data/sample1.yaml
bagofchips-0.0.1.dist-info/METADATA
bagofchips-0.0.1.dist-info/WHEEL
bagofchips-0.0.1.dist-info/entry_points.txt
bagofchips-0.0.1.dist-info/top_level.txt
bagofchips-0.0.1.dist-info/RECORD
