Metadata-Version: 2.1
Name: bagofchips
Version: 0.0.1
Summary: All that and a bag of
Author-email: James Kennington <jmk7376@psu.edu>
License: MPL-2.0
Project-URL: Homepage, https://git.ligo.org/james.kennington/chips
Project-URL: Documentation, https://docs.ligo.org/james.kennington/chips
Classifier: Programming Language :: Python :: 3
Classifier: License :: OSI Approved :: Mozilla Public License 2.0 (MPL 2.0)
Classifier: Operating System :: OS Independent
Requires-Python: >=3.10
Requires-Dist: pyyaml
Requires-Dist: lalsuite
Requires-Dist: python-ligo-lw
Requires-Dist: h5py
Requires-Dist: gwsci-manifold
Provides-Extra: dev
Requires-Dist: bagofchips[docs]; extra == "dev"
Requires-Dist: bagofchips[lint]; extra == "dev"
Requires-Dist: bagofchips[test]; extra == "dev"
Provides-Extra: docs
Requires-Dist: furo; extra == "docs"
Requires-Dist: myst-parser; extra == "docs"
Requires-Dist: sphinx; extra == "docs"
Provides-Extra: lint
Requires-Dist: black; extra == "lint"
Requires-Dist: flake8; extra == "lint"
Requires-Dist: flake8-bandit; extra == "lint"
Requires-Dist: flake8-black; extra == "lint"
Requires-Dist: flake8-bugbear; extra == "lint"
Requires-Dist: flake8-future-annotations; extra == "lint"
Requires-Dist: flake8-isort; extra == "lint"
Requires-Dist: flake8-logging-format; extra == "lint"
Requires-Dist: isort; extra == "lint"
Requires-Dist: mypy; extra == "lint"
Requires-Dist: mypy-extensions; extra == "lint"
Provides-Extra: test
Requires-Dist: pytest; extra == "test"
Requires-Dist: pytest-cov; extra == "test"
